{ "Data": [{ "SUBJECT": "", "CLOSE5": "N", "CLOSE4": "N", "SBB": "01", "HAKBB": "MAT2017-08", "CLOSE1": "N", "PSOSOKNA": "이과대학 수학", "OUTER_YN": "X", "CLOSE3": "N", "CLOSE2": "N", "JONG": "3", "GUBUN": "ⓖ⒝", "INTER": "", "HY": "2020", "BB": "08", "ONAME2": "기계공학전공", "NEWHAKNO": "C00270", "WEIGHT": "2000", "LINK": "", "KNA": "공학수학(4)", "HAKNO": "MAT2017", "MILEYN": "", "DOMAIN": "H1", "HAKYOUN": "2", "HAKJUM": "3", "ROOM": "동영상콘텐츠/실시간온라인(동영상콘텐츠(실시간온라인)", "PROF": "신안숙", "HG": "2", "TIME": "화2,3,목2/화2,3,목2(목3(목3)", "BAN": "0", "OCODE1": "s1104000H1", "HAKBBSBB": "MAT2017-08-01", "CLOSE": "", "SCOPE": "", "SEC": "", "JONGNM": "전기", "HYHG": "20202", "FIELD": "", "PRTYPE2": "3", "OHAKKWA": "04201", "EKNA": "ENGINEERING MATHEMATICS(4)", "MILE2YN": "", "NO_SLI": "Y" }, { "SUBJECT": "", "CLOSE5": "N", "CLOSE4": "N", "SBB": "02", "HAKBB": "MAT2017-08", "CLOSE1": "N", "PSOSOKNA": "이과대학 수학", "OUTER_YN": "X", "CLOSE3": "N", "CLOSE2": "N", "JONG": "3", "GUBUN": "ⓖ⒝", "INTER": "", "HY": "2020", "BB": "08", "ONAME2": "기계공학전공", "NEWHAKNO": "C00270", "WEIGHT": "2000", "LINK": "", "KNA": "공학수학(4)", "HAKNO": "MAT2017", "MILEYN": "", "DOMAIN": "H1", "HAKYOUN": "2", "HAKJUM": "3", "ROOM": "동영상콘텐츠/실시간온라인(동영상콘텐츠(실시간온라인)", "PROF": "신안숙", "HG": "2", "TIME": "화2,3,목2/화2,3,목2(목3(목3)", "BAN": "0", "OCODE1": "s1104000H1", "HAKBBSBB": "MAT2017-08-02", "CLOSE": "", "SCOPE": "", "SEC": "", "JONGNM": "전기", "HYHG": "20202", "FIELD": "", "PRTYPE2": "3", "OHAKKWA": "04201", "EKNA": "ENGINEERING MATHEMATICS(4)", "MILE2YN": "", "NO_SLI": "Y" }, { "SUBJECT": "", "CLOSE5": "N", "CLOSE4": "N", "SBB": "01", "HAKBB": "MAT2017-09", "CLOSE1": "N", "PSOSOKNA": "이과대학 수학", "OUTER_YN": "X", "CLOSE3": "N", "CLOSE2": "N", "JONG": "3", "GUBUN": "ⓖ⒝", "INTER": "", "HY": "2020", "BB": "09", "ONAME2": "기계공학전공", "NEWHAKNO": "C00270", "WEIGHT": "2000", "LINK": "", "KNA": "공학수학(4)", "HAKNO": "MAT2017", "MILEYN": "", "DOMAIN": "H1", "HAKYOUN": "2", "HAKJUM": "3", "ROOM": "동영상콘텐츠/실시간온라인(동영상콘텐츠(실시간온라인)", "PROF": "황숙정", "HG": "2", "TIME": "수2,3,목2/수2,3,목2(목3(목3)", "BAN": "0", "OCODE1": "s1104000H1", "HAKBBSBB": "MAT2017-09-01", "CLOSE": "", "SCOPE": "", "SEC": "", "JONGNM": "전기", "HYHG": "20202", "FIELD": "", "PRTYPE2": "3", "OHAKKWA": "04201", "EKNA": "ENGINEERING MATHEMATICS(4)", "MILE2YN": "", "NO_SLI": "Y" }, { "SUBJECT": "", "CLOSE5": "N", "CLOSE4": "N", "SBB": "02", "HAKBB": "MAT2017-09", "CLOSE1": "N", "PSOSOKNA": "이과대학 수학", "OUTER_YN": "X", "CLOSE3": "N", "CLOSE2": "N", "JONG": "3", "GUBUN": "ⓖ⒝", "INTER": "", "HY": "2020", "BB": "09", "ONAME2": "기계공학전공", "NEWHAKNO": "C00270", "WEIGHT": "2000", "LINK": "", "KNA": "공학수학(4)", "HAKNO": "MAT2017", "MILEYN": "", "DOMAIN": "H1", "HAKYOUN": "2", "HAKJUM": "3", "ROOM": "동영상콘텐츠/실시간온라인(동영상콘텐츠(실시간온라인)", "PROF": "황숙정", "HG": "2", "TIME": "수2,3,목2/수2,3,목2(목3(목3)", "BAN": "0", "OCODE1": "s1104000H1", "HAKBBSBB": "MAT2017-09-02", "CLOSE": "", "SCOPE": "", "SEC": "", "JONGNM": "전기", "HYHG": "20202", "FIELD": "", "PRTYPE2": "3", "OHAKKWA": "04201", "EKNA": "ENGINEERING MATHEMATICS(4)", "MILE2YN": "", "NO_SLI": "Y" }, { "SUBJECT": "", "CLOSE5": "N", "CLOSE4": "N", "SBB": "00", "HAKBB": "MEU2105-01", "CLOSE1": "N", "PSOSOKNA": "공과대학 기계공학과", "OUTER_YN": "X", "CLOSE3": "N", "CLOSE2": "N", "JONG": "4", "GUBUN": "ⓗ⒜", "INTER": "", "HY": "2020", "BB": "01", "ONAME2": "기계공학전공", "NEWHAKNO": "D01168", "WEIGHT": "2000", "LINK": "", "KNA": "기계공학실험(1)", "HAKNO": "MEU2105", "MILEYN": "", "DOMAIN": "H1", "HAKYOUN": "2", "HAKJUM": "3", "ROOM": "동영상콘텐츠/공D604", "PROF": "전성찬,김우철,최종은,이형석", "HG": "2", "TIME": "월9,10/목10,11,12", "BAN": "0", "OCODE1": "s1104000H1", "HAKBBSBB": "MEU2105-01-00", "CLOSE": "", "SCOPE": "", "SEC": "", "JONGNM": "전필", "HYHG": "20202", "FIELD": "", "PRTYPE2": "3", "OHAKKWA": "04201", "EKNA": "MECHANICAL ENGINEERING LABORATORY I", "MILE2YN": "", "NO_SLI": "Y" }, { "SUBJECT": "", "CLOSE5": "N", "CLOSE4": "N", "SBB": "00", "HAKBB": "MEU2105-02", "CLOSE1": "N", "PSOSOKNA": "공과대학 기계공학과", "OUTER_YN": "X", "CLOSE3": "N", "CLOSE2": "N", "JONG": "4", "GUBUN": "ⓗ⒜", "INTER": "", "HY": "2020", "BB": "02", "ONAME2": "기계공학전공", "NEWHAKNO": "D01168", "WEIGHT": "2000", "LINK": "", "KNA": "기계공학실험(1)", "HAKNO": "MEU2105", "MILEYN": "", "DOMAIN": "H1", "HAKYOUN": "2", "HAKJUM": "3", "ROOM": "동영상콘텐츠/공D402", "PROF": "김우철,최종은,이형석,전성찬", "HG": "2", "TIME": "월9,10/목10,11,12", "BAN": "0", "OCODE1": "s1104000H1", "HAKBBSBB": "MEU2105-02-00", "CLOSE": "", "SCOPE": "", "SEC": "", "JONGNM": "전필", "HYHG": "20202", "FIELD": "", "PRTYPE2": "3", "OHAKKWA": "04201", "EKNA": "MECHANICAL ENGINEERING LABORATORY I", "MILE2YN": "", "NO_SLI": "Y" }, { "SUBJECT": "", "CLOSE5": "N", "CLOSE4": "N", "SBB": "00", "HAKBB": "MEU2105-03", "CLOSE1": "N", "PSOSOKNA": "공과대학 기계공학과", "OUTER_YN": "X", "CLOSE3": "N", "CLOSE2": "N", "JONG": "4", "GUBUN": "ⓗ⒜", "INTER": "", "HY": "2020", "BB": "03", "ONAME2": "기계공학전공", "NEWHAKNO": "D01168", "WEIGHT": "2000", "LINK": "", "KNA": "기계공학실험(1)", "HAKNO": "MEU2105", "MILEYN": "", "DOMAIN": "H1", "HAKYOUN": "2", "HAKJUM": "3", "ROOM": "동영상콘텐츠/공D509", "PROF": "최종은,이형석,전성찬,김우철", "HG": "2", "TIME": "월9,10/목10,11,12", "BAN": "0", "OCODE1": "s1104000H1", "HAKBBSBB": "MEU2105-03-00", "CLOSE": "", "SCOPE": "", "SEC": "", "JONGNM": "전필", "HYHG": "20202", "FIELD": "", "PRTYPE2": "3", "OHAKKWA": "04201", "EKNA": "MECHANICAL ENGINEERING LABORATORY I", "MILE2YN": "", "NO_SLI": "Y" }, { "SUBJECT": "", "CLOSE5": "N", "CLOSE4": "N", "SBB": "00", "HAKBB": "MEU2105-04", "CLOSE1": "N", "PSOSOKNA": "공과대학 기계공학과", "OUTER_YN": "X", "CLOSE3": "N", "CLOSE2": "N", "JONG": "4", "GUBUN": "ⓗ⒜", "INTER": "", "HY": "2020", "BB": "04", "ONAME2": "기계공학전공", "NEWHAKNO": "D01168", "WEIGHT": "2000", "LINK": "", "KNA": "기계공학실험(1)", "HAKNO": "MEU2105", "MILEYN": "", "DOMAIN": "H1", "HAKYOUN": "2", "HAKJUM": "3", "ROOM": "동영상콘텐츠/공D602", "PROF": "이형석,전성찬,김우철,최종은", "HG": "2", "TIME": "월9,10/목10,11,12", "BAN": "0", "OCODE1": "s1104000H1", "HAKBBSBB": "MEU2105-04-00", "CLOSE": "", "SCOPE": "", "SEC": "", "JONGNM": "전필", "HYHG": "20202", "FIELD": "", "PRTYPE2": "3", "OHAKKWA": "04201", "EKNA": "MECHANICAL ENGINEERING LABORATORY I", "MILE2YN": "", "NO_SLI": "Y" }, { "SUBJECT": "", "CLOSE5": "N", "CLOSE4": "N", "SBB": "00", "HAKBB": "MEU2640-01", "CLOSE1": "N", "PSOSOKNA": "대학원 계산과학공학과", "OUTER_YN": "X", "CLOSE3": "N", "CLOSE2": "N", "JONG": "4", "GUBUN": "ⓡ⒜", "INTER": "", "HY": "2020", "BB": "01", "ONAME2": "기계공학전공", "NEWHAKNO": "D00555", "WEIGHT": "2000", "LINK": "", "KNA": "유체역학", "HAKNO": "MEU2640", "MILEYN": "", "DOMAIN": "H1", "HAKYOUN": "2", "HAKJUM": "3", "ROOM": "실시간온라인", "PROF": "이창훈", "HG": "2", "TIME": "화1,목5,6", "BAN": "0", "OCODE1": "s1104000H1", "HAKBBSBB": "MEU2640-01-00", "CLOSE": "", "SCOPE": "", "SEC": "", "JONGNM": "전필", "HYHG": "20202", "FIELD": "", "PRTYPE2": "3", "OHAKKWA": "04201", "EKNA": "FLUID MECHANICS", "MILE2YN": "", "NO_SLI": "Y" }, { "SUBJECT": "", "CLOSE5": "N", "CLOSE4": "N", "SBB": "00", "HAKBB": "MEU2640-02", "CLOSE1": "N", "PSOSOKNA": "공과대학 기계공학과", "OUTER_YN": "X", "CLOSE3": "N", "CLOSE2": "N", "JONG": "4", "GUBUN": "ⓡ⒜", "INTER": "", "HY": "2020", "BB": "02", "ONAME2": "기계공학전공", "NEWHAKNO": "D00555", "WEIGHT": "2000", "LINK": "", "KNA": "유체역학", "HAKNO": "MEU2640", "MILEYN": "", "DOMAIN": "H1", "HAKYOUN": "2", "HAKJUM": "3", "ROOM": "실시간온라인", "PROF": "이준상,김영우", "HG": "2", "TIME": "화1,목5,6", "BAN": "0", "OCODE1": "s1104000H1", "HAKBBSBB": "MEU2640-02-00", "CLOSE": "", "SCOPE": "", "SEC": "", "JONGNM": "전필", "HYHG": "20202", "FIELD": "", "PRTYPE2": "3", "OHAKKWA": "04201", "EKNA": "FLUID MECHANICS", "MILE2YN": "", "NO_SLI": "Y" }, { "SUBJECT": "", "CLOSE5": "N", "CLOSE4": "N", "SBB": "00", "HAKBB": "MEU2650-01", "CLOSE1": "N", "PSOSOKNA": "공과대학 기계공학과", "OUTER_YN": "X", "CLOSE3": "N", "CLOSE2": "N", "JONG": "4", "GUBUN": "ⓙ⒜", "INTER": "", "HY": "2020", "BB": "01", "ONAME2": "기계공학전공", "NEWHAKNO": "D00273", "WEIGHT": "2000", "LINK": "", "KNA": "동역학", "HAKNO": "MEU2650", "MILEYN": "", "DOMAIN": "H1", "HAKYOUN": "2", "HAKJUM": "3", "ROOM": "공B040/실시간온라인/동영상콘텐츠", "PROF": "박노철", "HG": "2", "TIME": "화5,6/목1/목1", "BAN": "0", "OCODE1": "s1104000H1", "HAKBBSBB": "MEU2650-01-00", "CLOSE": "", "SCOPE": "", "SEC": "", "JONGNM": "전필", "HYHG": "20202", "FIELD": "", "PRTYPE2": "3", "OHAKKWA": "04201", "EKNA": "DYNAMICS", "MILE2YN": "", "NO_SLI": "Y" }, { "SUBJECT": "", "CLOSE5": "N", "CLOSE4": "N", "SBB": "00", "HAKBB": "MEU2650-02", "CLOSE1": "N", "PSOSOKNA": "공과대학 기계공학과", "OUTER_YN": "O", "CLOSE3": "N", "CLOSE2": "N", "JONG": "4", "GUBUN": "ⓡ②⒝", "INTER": "", "HY": "2020", "BB": "02", "ONAME2": "기계공학전공", "NEWHAKNO": "D00273", "WEIGHT": "2000", "LINK": "", "KNA": "동역학", "HAKNO": "MEU2650", "MILEYN": "", "DOMAIN": "H1", "HAKYOUN": "2", "HAKJUM": "3", "ROOM": "실시간온라인", "PROF": "엄원석", "HG": "2", "TIME": "화5,6,목1", "BAN": "0", "OCODE1": "s1104000H1", "HAKBBSBB": "MEU2650-02-00", "CLOSE": "", "SCOPE": "", "SEC": "", "JONGNM": "전필", "HYHG": "20202", "FIELD": "", "PRTYPE2": "3", "OHAKKWA": "04201", "EKNA": "DYNAMICS", "MILE2YN": "", "NO_SLI": "" }, { "SUBJECT": "", "CLOSE5": "N", "CLOSE4": "N", "SBB": "00", "HAKBB": "MEU2001-01", "CLOSE1": "N", "PSOSOKNA": "공과대학 기계공학과", "OUTER_YN": "X", "CLOSE3": "N", "CLOSE2": "N", "JONG": "5", "GUBUN": "ⓑ⒞", "INTER": "", "HY": "2020", "BB": "01", "ONAME2": "기계공학전공", "NEWHAKNO": "D10001", "WEIGHT": "2000", "LINK": "", "KNA": "주니어세미나(몬테카를로방법기초소개)", "HAKNO": "MEU2001", "MILEYN": "", "DOMAIN": "H1", "HAKYOUN": "2", "HAKJUM": "1", "ROOM": "동영상콘텐츠", "PROF": "강건욱", "HG": "2", "TIME": "화3", "BAN": "0", "OCODE1": "s1104000H1", "HAKBBSBB": "MEU2001-01-00", "CLOSE": "", "SCOPE": "", "SEC": "", "JONGNM": "전선", "HYHG": "20202", "FIELD": "", "PRTYPE2": "3", "OHAKKWA": "04201", "EKNA": "JUNIOR SEMINAR", "MILE2YN": "", "NO_SLI": "Y" }, { "SUBJECT": "", "CLOSE5": "N", "CLOSE4": "N", "SBB": "00", "HAKBB": "MEU2001-02", "CLOSE1": "N", "PSOSOKNA": "공과대학 기계공학과", "OUTER_YN": "X", "CLOSE3": "N", "CLOSE2": "N", "JONG": "5", "GUBUN": "ⓚ⒞", "INTER": "", "HY": "2020", "BB": "02", "ONAME2": "기계공학전공", "NEWHAKNO": "D10001", "WEIGHT": "2000", "LINK": "", "KNA": "주니어세미나(알려지지않은컴퓨터의진화과정뒷이야기)", "HAKNO": "MEU2001", "MILEYN": "", "DOMAIN": "H1", "HAKYOUN": "2", "HAKJUM": "1", "ROOM": "공D402", "PROF": "이수홍", "HG": "2", "TIME": "화6", "BAN": "0", "OCODE1": "s1104000H1", "HAKBBSBB": "MEU2001-02-00", "CLOSE": "", "SCOPE": "", "SEC": "", "JONGNM": "전선", "HYHG": "20202", "FIELD": "", "PRTYPE2": "3", "OHAKKWA": "04201", "EKNA": "JUNIOR SEMINAR", "MILE2YN": "", "NO_SLI": "Y" }, { "SUBJECT": "", "CLOSE5": "N", "CLOSE4": "N", "SBB": "00", "HAKBB": "MEU2001-03", "CLOSE1": "N", "PSOSOKNA": "공과대학 기계공학과", "OUTER_YN": "X", "CLOSE3": "N", "CLOSE2": "N", "JONG": "5", "GUBUN": "ⓚ⒞", "INTER": "", "HY": "2020", "BB": "03", "ONAME2": "기계공학전공", "NEWHAKNO": "D10001", "WEIGHT": "2000", "LINK": "", "KNA": "주니어세미나(기계공학과생체공학의만남)", "HAKNO": "MEU2001", "MILEYN": "", "DOMAIN": "H1", "HAKYOUN": "2", "HAKJUM": "1", "ROOM": "공D509", "PROF": "이형석", "HG": "2", "TIME": "목3", "BAN": "0", "OCODE1": "s1104000H1", "HAKBBSBB": "MEU2001-03-00", "CLOSE": "", "SCOPE": "", "SEC": "", "JONGNM": "전선", "HYHG": "20202", "FIELD": "", "PRTYPE2": "3", "OHAKKWA": "04201", "EKNA": "JUNIOR SEMINAR", "MILE2YN": "", "NO_SLI": "Y" }, { "SUBJECT": "", "CLOSE5": "N", "CLOSE4": "N", "SBB": "00", "HAKBB": "MEU2001-04", "CLOSE1": "N", "PSOSOKNA": "공과대학 기계공학과", "OUTER_YN": "X", "CLOSE3": "N", "CLOSE2": "N", "JONG": "5", "GUBUN": "ⓚ⒞", "INTER": "", "HY": "2020", "BB": "04", "ONAME2": "기계공학전공", "NEWHAKNO": "D10001", "WEIGHT": "2000", "LINK": "", "KNA": "주니어세미나(북극곰마술학교)", "HAKNO": "MEU2001", "MILEYN": "", "DOMAIN": "H1", "HAKYOUN": "2", "HAKJUM": "1", "ROOM": "공D601", "PROF": "차성운", "HG": "2", "TIME": "수6", "BAN": "0", "OCODE1": "s1104000H1", "HAKBBSBB": "MEU2001-04-00", "CLOSE": "", "SCOPE": "", "SEC": "", "JONGNM": "전선", "HYHG": "20202", "FIELD": "", "PRTYPE2": "3", "OHAKKWA": "04201", "EKNA": "JUNIOR SEMINAR", "MILE2YN": "", "NO_SLI": "Y" }, { "SUBJECT": "", "CLOSE5": "N", "CLOSE4": "N", "SBB": "00", "HAKBB": "MEU2002-02", "CLOSE1": "N", "PSOSOKNA": "공과대학 기계공학과", "OUTER_YN": "X", "CLOSE3": "N", "CLOSE2": "N", "JONG": "5", "GUBUN": "ⓚ⒞", "INTER": "", "HY": "2020", "BB": "02", "ONAME2": "기계공학전공", "NEWHAKNO": "D01176", "WEIGHT": "2000", "LINK": "", "KNA": "UT세미나(광합성과에너지,전기화학으로의연결고리)", "HAKNO": "MEU2002", "MILEYN": "", "DOMAIN": "H1", "HAKYOUN": "2", "HAKJUM": "1", "ROOM": "공A683", "PROF": "김용재", "HG": "2", "TIME": "수8", "BAN": "0", "OCODE1": "s1104000H1", "HAKBBSBB": "MEU2002-02-00", "CLOSE": "", "SCOPE": "", "SEC": "", "JONGNM": "전선", "HYHG": "20202", "FIELD": "", "PRTYPE2": "3", "OHAKKWA": "04201", "EKNA": "UNDERGRADUATE TUTORIAL SEMINAR", "MILE2YN": "", "NO_SLI": "Y" }, { "SUBJECT": "", "CLOSE5": "N", "CLOSE4": "N", "SBB": "00", "HAKBB": "MEU2002-03", "CLOSE1": "N", "PSOSOKNA": "공과대학 기계공학과", "OUTER_YN": "X", "CLOSE3": "N", "CLOSE2": "N", "JONG": "5", "GUBUN": "ⓚ⒞", "INTER": "", "HY": "2020", "BB": "03", "ONAME2": "기계공학전공", "NEWHAKNO": "D01176", "WEIGHT": "2000", "LINK": "", "KNA": "UT세미나(마이크로니들의소개와응용)", "HAKNO": "MEU2002", "MILEYN": "", "DOMAIN": "H1", "HAKYOUN": "2", "HAKJUM": "1", "ROOM": "공A683", "PROF": "박승현", "HG": "2", "TIME": "화8", "BAN": "0", "OCODE1": "s1104000H1", "HAKBBSBB": "MEU2002-03-00", "CLOSE": "", "SCOPE": "", "SEC": "", "JONGNM": "전선", "HYHG": "20202", "FIELD": "", "PRTYPE2": "3", "OHAKKWA": "04201", "EKNA": "UNDERGRADUATE TUTORIAL SEMINAR", "MILE2YN": "", "NO_SLI": "Y" }, { "SUBJECT": "", "CLOSE5": "N", "CLOSE4": "N", "SBB": "00", "HAKBB": "MEU3300-01", "CLOSE1": "N", "PSOSOKNA": "공과대학 기계공학과", "OUTER_YN": "X", "CLOSE3": "N", "CLOSE2": "N", "JONG": "4", "GUBUN": "ⓗ⒜", "INTER": "", "HY": "2020", "BB": "01", "ONAME2": "기계공학전공", "NEWHAKNO": "D00980", "WEIGHT": "3000", "LINK": "", "KNA": "창의설계프로젝트(2)(종합설계)", "HAKNO": "MEU3300", "MILEYN": "", "DOMAIN": "H1", "HAKYOUN": "3", "HAKJUM": "3", "ROOM": "공D604/동영상콘텐츠", "PROF": "이수홍", "HG": "2", "TIME": "수2,3/금2,3", "BAN": "0", "OCODE1": "s1104000H1", "HAKBBSBB": "MEU3300-01-00", "CLOSE": "", "SCOPE": "", "SEC": "", "JONGNM": "전필", "HYHG": "20202", "FIELD": "", "PRTYPE2": "3", "OHAKKWA": "04201", "EKNA": "CREATIVE MECHANICAL ENGINEERING DESIGN(2)", "MILE2YN": "", "NO_SLI": "Y" }, { "SUBJECT": "", "CLOSE5": "N", "CLOSE4": "N", "SBB": "00", "HAKBB": "MEU3300-02", "CLOSE1": "N", "PSOSOKNA": "공과대학 기계공학과", "OUTER_YN": "X", "CLOSE3": "N", "CLOSE2": "N", "JONG": "4", "GUBUN": "ⓚ②⒝", "INTER": "", "HY": "2020", "BB": "02", "ONAME2": "기계공학전공", "NEWHAKNO": "D00980", "WEIGHT": "3000", "LINK": "", "KNA": "창의설계프로젝트(2)(종합설계)", "HAKNO": "MEU3300", "MILEYN": "", "DOMAIN": "H1", "HAKYOUN": "3", "HAKJUM": "3", "ROOM": "공D402", "PROF": "정효일", "HG": "2", "TIME": "수2,3,금2,3", "BAN": "0", "OCODE1": "s1104000H1", "HAKBBSBB": "MEU3300-02-00", "CLOSE": "", "SCOPE": "", "SEC": "", "JONGNM": "전필", "HYHG": "20202", "FIELD": "", "PRTYPE2": "3", "OHAKKWA": "04201", "EKNA": "CREATIVE MECHANICAL ENGINEERING DESIGN(2)", "MILE2YN": "", "NO_SLI": "Y" }, { "SUBJECT": "", "CLOSE5": "N", "CLOSE4": "N", "SBB": "00", "HAKBB": "MEU3300-03", "CLOSE1": "N", "PSOSOKNA": "공과대학 기계공학과", "OUTER_YN": "X", "CLOSE3": "N", "CLOSE2": "N", "JONG": "4", "GUBUN": "ⓘ⒜", "INTER": "", "HY": "2020", "BB": "03", "ONAME2": "기계공학전공", "NEWHAKNO": "D00980", "WEIGHT": "3000", "LINK": "", "KNA": "창의설계프로젝트(2)(종합설계)", "HAKNO": "MEU3300", "MILEYN": "", "DOMAIN": "H1", "HAKYOUN": "3", "HAKJUM": "3", "ROOM": "실시간온라인/공D509(공A213)", "PROF": "이종수", "HG": "2", "TIME": "수2,3/수2,3,금2,3(금2,3)", "BAN": "0", "OCODE1": "s1104000H1", "HAKBBSBB": "MEU3300-03-00", "CLOSE": "", "SCOPE": "", "SEC": "", "JONGNM": "전필", "HYHG": "20202", "FIELD": "", "PRTYPE2": "3", "OHAKKWA": "04201", "EKNA": "CREATIVE MECHANICAL ENGINEERING DESIGN(2)", "MILE2YN": "", "NO_SLI": "Y" }, { "SUBJECT": "", "CLOSE5": "N", "CLOSE4": "N", "SBB": "00", "HAKBB": "MEU3300-04", "CLOSE1": "N", "PSOSOKNA": "공과대학 기계공학과", "OUTER_YN": "X", "CLOSE3": "N", "CLOSE2": "N", "JONG": "4", "GUBUN": "ⓚ②⒝", "INTER": "", "HY": "2020", "BB": "04", "ONAME2": "기계공학전공", "NEWHAKNO": "D00980", "WEIGHT": "3000", "LINK": "", "KNA": "창의설계프로젝트(2)(종합설계)", "HAKNO": "MEU3300", "MILEYN": "", "DOMAIN": "H1", "HAKYOUN": "3", "HAKJUM": "3", "ROOM": "공A683(공B017)", "PROF": "홍종섭", "HG": "2", "TIME": "수2,3,금2,3(수2,3,금2,3)", "BAN": "0", "OCODE1": "s1104000H1", "HAKBBSBB": "MEU3300-04-00", "CLOSE": "", "SCOPE": "", "SEC": "", "JONGNM": "전필", "HYHG": "20202", "FIELD": "", "PRTYPE2": "3", "OHAKKWA": "04201", "EKNA": "CREATIVE MECHANICAL ENGINEERING DESIGN(2)", "MILE2YN": "", "NO_SLI": "Y" }, { "SUBJECT": "", "CLOSE5": "N", "CLOSE4": "N", "SBB": "00", "HAKBB": "MEU3003-01", "CLOSE1": "N", "PSOSOKNA": "공과대학 기계공학과", "OUTER_YN": "O", "CLOSE3": "N", "CLOSE2": "N", "JONG": "3", "GUBUN": "ⓗ②⒝", "INTER": "", "HY": "2020", "BB": "01", "ONAME2": "기계공학전공", "NEWHAKNO": "D01002", "WEIGHT": "3000", "LINK": "", "KNA": "공학수치해석", "HAKNO": "MEU3003", "MILEYN": "", "DOMAIN": "H1", "HAKYOUN": "3,4", "HAKJUM": "3", "ROOM": "공D402/동영상콘텐츠", "PROF": "강건욱", "HG": "2", "TIME": "화5/목5,6", "BAN": "0", "OCODE1": "s1104000H1", "HAKBBSBB": "MEU3003-01-00", "CLOSE": "", "SCOPE": "", "SEC": "", "JONGNM": "전기", "HYHG": "20202", "FIELD": "", "PRTYPE2": "3", "OHAKKWA": "04201", "EKNA": "ENGINEERING NUMERICAL ANALYSIS", "MILE2YN": "", "NO_SLI": "Y" }, { "SUBJECT": "", "CLOSE5": "N", "CLOSE4": "N", "SBB": "00", "HAKBB": "MEU3007-01", "CLOSE1": "N", "PSOSOKNA": "공과대학 기계공학과", "OUTER_YN": "X", "CLOSE3": "N", "CLOSE2": "N", "JONG": "5", "GUBUN": "ⓚ⒞", "INTER": "", "HY": "2020", "BB": "01", "ONAME2": "기계공학전공", "NEWHAKNO": "D01163", "WEIGHT": "3000", "LINK": "", "KNA": "학부연구(2)", "HAKNO": "MEU3007", "MILEYN": "", "DOMAIN": "H1", "HAKYOUN": "3,4", "HAKJUM": "1", "ROOM": "공D402", "PROF": "주철민", "HG": "2", "TIME": "금5", "BAN": "0", "OCODE1": "s1104000H1", "HAKBBSBB": "MEU3007-01-00", "CLOSE": "", "SCOPE": "", "SEC": "", "JONGNM": "전선", "HYHG": "20202", "FIELD": "", "PRTYPE2": "3", "OHAKKWA": "04201", "EKNA": "Undergraduate Independent Study II", "MILE2YN": "", "NO_SLI": "Y" }, { "SUBJECT": "", "CLOSE5": "N", "CLOSE4": "N", "SBB": "00", "HAKBB": "MEU3011-01", "CLOSE1": "N", "PSOSOKNA": "공과대학 기계공학과", "OUTER_YN": "X", "CLOSE3": "N", "CLOSE2": "N", "JONG": "5", "GUBUN": "ⓓⓙ⒜", "INTER": "", "HY": "2020", "BB": "01", "ONAME2": "기계공학전공", "NEWHAKNO": "D00960", "WEIGHT": "3000", "LINK": "", "KNA": "에너지동력공학", "HAKNO": "MEU3011", "MILEYN": "", "DOMAIN": "H1", "HAKYOUN": "3,4", "HAKJUM": "3", "ROOM": "공D509/동영상콘텐츠/실시간온라인(실시간온라인(공D509(동영상", "PROF": "조형희,송순호", "HG": "2", "TIME": "화5/화5,목1,2/화5,목1,2(화4(화4(화4)", "BAN": "0", "OCODE1": "s1104000H1", "HAKBBSBB": "MEU3011-01-00", "CLOSE": "", "SCOPE": "", "SEC": "", "JONGNM": "전선", "HYHG": "20202", "FIELD": "", "PRTYPE2": "3", "OHAKKWA": "04201", "EKNA": "ENERGY AND POWER ENGINEERING", "MILE2YN": "", "NO_SLI": "Y" }, { "SUBJECT": "", "CLOSE5": "N", "CLOSE4": "N", "SBB": "00", "HAKBB": "MEU3012-01", "CLOSE1": "N", "PSOSOKNA": "공과대학 기계공학과", "OUTER_YN": "X", "CLOSE3": "N", "CLOSE2": "N", "JONG": "5", "GUBUN": "ⓗ⒜", "INTER": "", "HY": "2020", "BB": "01", "ONAME2": "기계공학전공", "NEWHAKNO": "D00934", "WEIGHT": "3000", "LINK": "", "KNA": "광공학", "HAKNO": "MEU3012", "MILEYN": "", "DOMAIN": "H1", "HAKYOUN": "3,4", "HAKJUM": "3", "ROOM": "공D509/동영상콘텐츠", "PROF": "한재원", "HG": "2", "TIME": "화1/목5,6", "BAN": "0", "OCODE1": "s1104000H1", "HAKBBSBB": "MEU3012-01-00", "CLOSE": "", "SCOPE": "", "SEC": "", "JONGNM": "전선", "HYHG": "20202", "FIELD": "", "PRTYPE2": "3", "OHAKKWA": "04201", "EKNA": "OPTICAL ENGINEERING", "MILE2YN": "", "NO_SLI": "Y" }, { "SUBJECT": "", "CLOSE5": "N", "CLOSE4": "N", "SBB": "00", "HAKBB": "MEU3014-01", "CLOSE1": "N", "PSOSOKNA": "공과대학 기계공학과", "OUTER_YN": "X", "CLOSE3": "N", "CLOSE2": "N", "JONG": "5", "GUBUN": "ⓗ⒜", "INTER": "", "HY": "2020", "BB": "01", "ONAME2": "기계공학전공", "NEWHAKNO": "D00295", "WEIGHT": "3000", "LINK": "", "KNA": "메카트로닉스", "HAKNO": "MEU3014", "MILEYN": "", "DOMAIN": "H1", "HAKYOUN": "3,4", "HAKJUM": "3", "ROOM": "공D509/동영상콘텐츠(공B017)", "PROF": "민병권", "HG": "2", "TIME": "화6,7/목7(화6,7,목7)", "BAN": "0", "OCODE1": "s1104000H1", "HAKBBSBB": "MEU3014-01-00", "CLOSE": "", "SCOPE": "", "SEC": "", "JONGNM": "전선", "HYHG": "20202", "FIELD": "", "PRTYPE2": "3", "OHAKKWA": "04201", "EKNA": "MECHATRONICS", "MILE2YN": "", "NO_SLI": "Y" }, { "SUBJECT": "", "CLOSE5": "N", "CLOSE4": "N", "SBB": "00", "HAKBB": "MEU3014-02", "CLOSE1": "N", "PSOSOKNA": "공과대학 기계공학과", "OUTER_YN": "X", "CLOSE3": "N", "CLOSE2": "N", "JONG": "5", "GUBUN": "ⓗ⒜", "INTER": "", "HY": "2020", "BB": "02", "ONAME2": "기계공학전공", "NEWHAKNO": "D00295", "WEIGHT": "3000", "LINK": "", "KNA": "메카트로닉스", "HAKNO": "MEU3014", "MILEYN": "", "DOMAIN": "H1", "HAKYOUN": "3,4", "HAKJUM": "3", "ROOM": "공A683/동영상콘텐츠(공A213(공A215)", "PROF": "윤준영", "HG": "2", "TIME": "화6,7/목7(화6,7,목7(화6,7,목7)", "BAN": "0", "OCODE1": "s1104000H1", "HAKBBSBB": "MEU3014-02-00", "CLOSE": "", "SCOPE": "", "SEC": "", "JONGNM": "전선", "HYHG": "20202", "FIELD": "", "PRTYPE2": "3", "OHAKKWA": "04201", "EKNA": "MECHATRONICS", "MILE2YN": "", "NO_SLI": "Y" }, { "SUBJECT": "", "CLOSE5": "N", "CLOSE4": "N", "SBB": "00", "HAKBB": "MEU3600-01", "CLOSE1": "N", "PSOSOKNA": "공과대학 기계공학과", "OUTER_YN": "X", "CLOSE3": "N", "CLOSE2": "N", "JONG": "5", "GUBUN": "ⓚ⒜", "INTER": "", "HY": "2020", "BB": "01", "ONAME2": "기계공학전공", "NEWHAKNO": "D00734", "WEIGHT": "3000", "LINK": "", "KNA": "응용고체역학", "HAKNO": "MEU3600", "MILEYN": "", "DOMAIN": "H1", "HAKYOUN": "3,4", "HAKJUM": "3", "ROOM": "공D604", "PROF": "장용훈", "HG": "2", "TIME": "화7,목2,3", "BAN": "0", "OCODE1": "s1104000H1", "HAKBBSBB": "MEU3600-01-00", "CLOSE": "", "SCOPE": "", "SEC": "", "JONGNM": "전선", "HYHG": "20202", "FIELD": "", "PRTYPE2": "3", "OHAKKWA": "04201", "EKNA": "ADVANCED MECHANICS OF MATERIALS", "MILE2YN": "", "NO_SLI": "Y" }, { "SUBJECT": "", "CLOSE5": "N", "CLOSE4": "N", "SBB": "00", "HAKBB": "MEU3600-02", "CLOSE1": "N", "PSOSOKNA": "공과대학 기계공학과", "OUTER_YN": "X", "CLOSE3": "N", "CLOSE2": "N", "JONG": "5", "GUBUN": "ⓗ⒜", "INTER": "", "HY": "2020", "BB": "02", "ONAME2": "기계공학전공", "NEWHAKNO": "D00734", "WEIGHT": "3000", "LINK": "", "KNA": "응용고체역학", "HAKNO": "MEU3600", "MILEYN": "", "DOMAIN": "H1", "HAKYOUN": "3,4", "HAKJUM": "3", "ROOM": "공D402/동영상콘텐츠", "PROF": "전흥재", "HG": "2", "TIME": "화7/목2,3", "BAN": "0", "OCODE1": "s1104000H1", "HAKBBSBB": "MEU3600-02-00", "CLOSE": "", "SCOPE": "", "SEC": "", "JONGNM": "전선", "HYHG": "20202", "FIELD": "", "PRTYPE2": "3", "OHAKKWA": "04201", "EKNA": "ADVANCED MECHANICS OF MATERIALS", "MILE2YN": "", "NO_SLI": "Y" }, { "SUBJECT": "", "CLOSE5": "N", "CLOSE4": "N", "SBB": "00", "HAKBB": "MEU3610-01", "CLOSE1": "N", "PSOSOKNA": "공과대학 기계공학과", "OUTER_YN": "X", "CLOSE3": "N", "CLOSE2": "N", "JONG": "5", "GUBUN": "ⓙ⒜", "INTER": "", "HY": "2020", "BB": "01", "ONAME2": "기계공학전공", "NEWHAKNO": "D00575", "WEIGHT": "3000", "LINK": "", "KNA": "응용열역학", "HAKNO": "MEU3610", "MILEYN": "", "DOMAIN": "H1", "HAKYOUN": "3,4", "HAKJUM": "3", "ROOM": "동영상콘텐츠/실시간온라인/공D604(공D604)", "PROF": "황정호", "HG": "2", "TIME": "화2,3/화2,3/목7(목8)", "BAN": "0", "OCODE1": "s1104000H1", "HAKBBSBB": "MEU3610-01-00", "CLOSE": "", "SCOPE": "", "SEC": "", "JONGNM": "전선", "HYHG": "20202", "FIELD": "", "PRTYPE2": "3", "OHAKKWA": "04201", "EKNA": "APPLIED THERMODYNAMICS", "MILE2YN": "", "NO_SLI": "" }, { "SUBJECT": "", "CLOSE5": "N", "CLOSE4": "N", "SBB": "00", "HAKBB": "MEU3610-02", "CLOSE1": "N", "PSOSOKNA": "공과대학 기계공학과", "OUTER_YN": "X", "CLOSE3": "N", "CLOSE2": "N", "JONG": "5", "GUBUN": "ⓖ⒜", "INTER": "", "HY": "2020", "BB": "02", "ONAME2": "기계공학전공", "NEWHAKNO": "D00575", "WEIGHT": "3000", "LINK": "", "KNA": "응용열역학", "HAKNO": "MEU3610", "MILEYN": "", "DOMAIN": "H1", "HAKYOUN": "3,4", "HAKJUM": "3", "ROOM": "동영상콘텐츠/실시간온라인(동영상콘텐츠(실시간온라인)", "PROF": "송순호", "HG": "2", "TIME": "화2,3,목7/화2,3,목7(목8(목8)", "BAN": "0", "OCODE1": "s1104000H1", "HAKBBSBB": "MEU3610-02-00", "CLOSE": "", "SCOPE": "", "SEC": "", "JONGNM": "전선", "HYHG": "20202", "FIELD": "", "PRTYPE2": "3", "OHAKKWA": "04201", "EKNA": "APPLIED THERMODYNAMICS", "MILE2YN": "", "NO_SLI": "Y" }, { "SUBJECT": "", "CLOSE5": "N", "CLOSE4": "N", "SBB": "00", "HAKBB": "MEU3630-01", "CLOSE1": "N", "PSOSOKNA": "공과대학 기계공학과", "OUTER_YN": "X", "CLOSE3": "N", "CLOSE2": "N", "JONG": "5", "GUBUN": "ⓖ⒜", "INTER": "", "HY": "2020", "BB": "01", "ONAME2": "기계공학전공", "NEWHAKNO": "D00172", "WEIGHT": "3000", "LINK": "", "KNA": "기계요소설계", "HAKNO": "MEU3630", "MILEYN": "", "DOMAIN": "H1", "HAKYOUN": "3,4", "HAKJUM": "3", "ROOM": "동영상콘텐츠/실시간온라인", "PROF": "유정훈", "HG": "2", "TIME": "월6,수6/수7", "BAN": "0", "OCODE1": "s1104000H1", "HAKBBSBB": "MEU3630-01-00", "CLOSE": "", "SCOPE": "", "SEC": "", "JONGNM": "전선", "HYHG": "20202", "FIELD": "", "PRTYPE2": "3", "OHAKKWA": "04201", "EKNA": "DESIGN OF MACHINE ELEMENT", "MILE2YN": "", "NO_SLI": "Y" }, { "SUBJECT": "", "CLOSE5": "N", "CLOSE4": "N", "SBB": "00", "HAKBB": "MEU3660-01", "CLOSE1": "N", "PSOSOKNA": "공과대학 기계공학과", "OUTER_YN": "X", "CLOSE3": "N", "CLOSE2": "N", "JONG": "5", "GUBUN": "ⓗ⒜", "INTER": "", "HY": "2020", "BB": "01", "ONAME2": "기계공학전공", "NEWHAKNO": "D00110", "WEIGHT": "3000", "LINK": "", "KNA": "공학재료", "HAKNO": "MEU3660", "MILEYN": "", "DOMAIN": "H1", "HAKYOUN": "3,4", "HAKJUM": "3", "ROOM": "동영상콘텐츠/공D604", "PROF": "김영주", "HG": "2", "TIME": "월5,6/수5", "BAN": "0", "OCODE1": "s1104000H1", "HAKBBSBB": "MEU3660-01-00", "CLOSE": "", "SCOPE": "", "SEC": "", "JONGNM": "전선", "HYHG": "20202", "FIELD": "", "PRTYPE2": "3", "OHAKKWA": "04201", "EKNA": "ENGINEERING MATERIALS", "MILE2YN": "", "NO_SLI": "Y" }, { "SUBJECT": "", "CLOSE5": "N", "CLOSE4": "N", "SBB": "00", "HAKBB": "MEU3680-01", "CLOSE1": "N", "PSOSOKNA": "공과대학 기계공학과", "OUTER_YN": "O", "CLOSE3": "N", "CLOSE2": "N", "JONG": "5", "GUBUN": "ⓗ⒜", "INTER": "", "HY": "2020", "BB": "01", "ONAME2": "기계공학전공", "NEWHAKNO": "D00961", "WEIGHT": "3000", "LINK": "", "KNA": "기계시스템제어", "HAKNO": "MEU3680", "MILEYN": "", "DOMAIN": "H1", "HAKYOUN": "3,4", "HAKJUM": "3", "ROOM": "동영상콘텐츠/공B040", "PROF": "양현석", "HG": "2", "TIME": "월7,8/수4", "BAN": "0", "OCODE1": "s1104000H1", "HAKBBSBB": "MEU3680-01-00", "CLOSE": "", "SCOPE": "", "SEC": "", "JONGNM": "전선", "HYHG": "20202", "FIELD": "", "PRTYPE2": "3", "OHAKKWA": "04201", "EKNA": "MECHANICAL SYSTEM CONTROL", "MILE2YN": "", "NO_SLI": "Y" }, { "SUBJECT": "", "CLOSE5": "N", "CLOSE4": "N", "SBB": "00", "HAKBB": "MEU3680-02", "CLOSE1": "N", "PSOSOKNA": "공과대학 기계공학과", "OUTER_YN": "X", "CLOSE3": "N", "CLOSE2": "N", "JONG": "5", "GUBUN": "ⓗ②⒝", "INTER": "", "HY": "2020", "BB": "02", "ONAME2": "기계공학전공", "NEWHAKNO": "D00961", "WEIGHT": "3000", "LINK": "", "KNA": "기계시스템제어", "HAKNO": "MEU3680", "MILEYN": "", "DOMAIN": "H1", "HAKYOUN": "3,4", "HAKJUM": "3", "ROOM": "공D604/동영상콘텐츠", "PROF": "김종백", "HG": "2", "TIME": "월7,8/수4", "BAN": "0", "OCODE1": "s1104000H1", "HAKBBSBB": "MEU3680-02-00", "CLOSE": "", "SCOPE": "", "SEC": "", "JONGNM": "전선", "HYHG": "20202", "FIELD": "", "PRTYPE2": "3", "OHAKKWA": "04201", "EKNA": "MECHANICAL SYSTEM CONTROL", "MILE2YN": "", "NO_SLI": "Y" }, { "SUBJECT": "", "CLOSE5": "N", "CLOSE4": "N", "SBB": "00", "HAKBB": "MEU3700-01", "CLOSE1": "N", "PSOSOKNA": "공과대학 기계공학과", "OUTER_YN": "O", "CLOSE3": "N", "CLOSE2": "N", "JONG": "5", "GUBUN": "ⓗ②⒝", "INTER": "", "HY": "2020", "BB": "01", "ONAME2": "기계공학전공", "NEWHAKNO": "D01019", "WEIGHT": "3000", "LINK": "", "KNA": "생체역학", "HAKNO": "MEU3700", "MILEYN": "", "DOMAIN": "H1", "HAKYOUN": "3,4", "HAKJUM": "3", "ROOM": "공D509/동영상콘텐츠", "PROF": "류원형", "HG": "2", "TIME": "월7/월8,수1", "BAN": "0", "OCODE1": "s1104000H1", "HAKBBSBB": "MEU3700-01-00", "CLOSE": "", "SCOPE": "", "SEC": "", "JONGNM": "전선", "HYHG": "20202", "FIELD": "", "PRTYPE2": "3", "OHAKKWA": "04201", "EKNA": "BIOMECHANICS", "MILE2YN": "", "NO_SLI": "Y" }, { "SUBJECT": "", "CLOSE5": "N", "CLOSE4": "N", "SBB": "00", "HAKBB": "MEU3710-01", "CLOSE1": "N", "PSOSOKNA": "공과대학 기계공학과", "OUTER_YN": "O", "CLOSE3": "N", "CLOSE2": "N", "JONG": "5", "GUBUN": "ⓡ②⒝", "INTER": "", "HY": "2020", "BB": "01", "ONAME2": "기계공학전공", "NEWHAKNO": "D00186", "WEIGHT": "3000", "LINK": "", "KNA": "나노기계공학", "HAKNO": "MEU3710", "MILEYN": "", "DOMAIN": "H1", "HAKYOUN": "3,4", "HAKJUM": "3", "ROOM": "실시간온라인", "PROF": "김경식", "HG": "2", "TIME": "월2,수6,7", "BAN": "0", "OCODE1": "s1104000H1", "HAKBBSBB": "MEU3710-01-00", "CLOSE": "", "SCOPE": "", "SEC": "", "JONGNM": "전선", "HYHG": "20202", "FIELD": "", "PRTYPE2": "3", "OHAKKWA": "04201", "EKNA": "NANO MECHANICAL ENGINEERING", "MILE2YN": "", "NO_SLI": "Y" }, { "SUBJECT": "", "CLOSE5": "N", "CLOSE4": "N", "SBB": "00", "HAKBB": "MEU4002-01", "CLOSE1": "N", "PSOSOKNA": "공과대학 기계공학과", "OUTER_YN": "X", "CLOSE3": "N", "CLOSE2": "N", "JONG": "5", "GUBUN": "ⓡ⒞", "INTER": "", "HY": "2020", "BB": "01", "ONAME2": "기계공학전공", "NEWHAKNO": "D00051", "WEIGHT": "4000", "LINK": "", "KNA": "기계공학세미나(2)", "HAKNO": "MEU4002", "MILEYN": "", "DOMAIN": "H1", "HAKYOUN": "3,4", "HAKJUM": "3", "ROOM": "실시간온라인", "PROF": "백윤수", "HG": "2", "TIME": "금8,9,10", "BAN": "0", "OCODE1": "s1104000H1", "HAKBBSBB": "MEU4002-01-00", "CLOSE": "", "SCOPE": "", "SEC": "", "JONGNM": "전선", "HYHG": "20202", "FIELD": "", "PRTYPE2": "3", "OHAKKWA": "04201", "EKNA": "MECHANICAL ENGINEERING SEMINAR II", "MILE2YN": "", "NO_SLI": "Y" }, { "SUBJECT": "", "CLOSE5": "N", "CLOSE4": "N", "SBB": "00", "HAKBB": "MEU4300-01", "CLOSE1": "N", "PSOSOKNA": "공과대학 기계공학과", "OUTER_YN": "X", "CLOSE3": "N", "CLOSE2": "N", "JONG": "4", "GUBUN": "ⓡ⒝", "INTER": "", "HY": "2020", "BB": "01", "ONAME2": "기계공학전공", "NEWHAKNO": "D00959", "WEIGHT": "4000", "LINK": "", "KNA": "창의제품설계(종합설계)", "HAKNO": "MEU4300", "MILEYN": "", "DOMAIN": "H1", "HAKYOUN": "4", "HAKJUM": "3", "ROOM": "실시간온라인", "PROF": "김대은,이형석", "HG": "2", "TIME": "화8,9,목8,9", "BAN": "0", "OCODE1": "s1104000H1", "HAKBBSBB": "MEU4300-01-00", "CLOSE": "", "SCOPE": "", "SEC": "", "JONGNM": "전필", "HYHG": "20202", "FIELD": "", "PRTYPE2": "3", "OHAKKWA": "04201", "EKNA": "CREATIVE PRODUCT DESIGN", "MILE2YN": "", "NO_SLI": "Y" }, { "SUBJECT": "", "CLOSE5": "N", "CLOSE4": "N", "SBB": "00", "HAKBB": "MEU4300-02", "CLOSE1": "N", "PSOSOKNA": "공과대학 기계공학과", "OUTER_YN": "X", "CLOSE3": "N", "CLOSE2": "N", "JONG": "4", "GUBUN": "ⓡ⒝", "INTER": "", "HY": "2020", "BB": "02", "ONAME2": "기계공학전공", "NEWHAKNO": "D00959", "WEIGHT": "4000", "LINK": "", "KNA": "창의제품설계(종합설계)", "HAKNO": "MEU4300", "MILEYN": "", "DOMAIN": "H1", "HAKYOUN": "4", "HAKJUM": "3", "ROOM": "실시간온라인", "PROF": "이형석,김대은", "HG": "2", "TIME": "화8,9,목8,9", "BAN": "0", "OCODE1": "s1104000H1", "HAKBBSBB": "MEU4300-02-00", "CLOSE": "", "SCOPE": "", "SEC": "", "JONGNM": "전필", "HYHG": "20202", "FIELD": "", "PRTYPE2": "3", "OHAKKWA": "04201", "EKNA": "CREATIVE PRODUCT DESIGN", "MILE2YN": "", "NO_SLI": "Y" }, { "SUBJECT": "", "CLOSE5": "N", "CLOSE4": "N", "SBB": "00", "HAKBB": "MEU4400-01", "CLOSE1": "N", "PSOSOKNA": "공과대학 기계공학과", "OUTER_YN": "X", "CLOSE3": "N", "CLOSE2": "N", "JONG": "4", "GUBUN": "ⓖ⒝", "INTER": "", "HY": "2020", "BB": "01", "ONAME2": "기계공학전공", "NEWHAKNO": "D00917", "WEIGHT": "4000", "LINK": "", "KNA": "연구논문", "HAKNO": "MEU4400", "MILEYN": "", "DOMAIN": "H1", "HAKYOUN": "4", "HAKJUM": "3", "ROOM": "동영상콘텐츠/실시간온라인", "PROF": "조형희,민병권,주철민", "HG": "2", "TIME": "월6/수5,6", "BAN": "0", "OCODE1": "s1104000H1", "HAKBBSBB": "MEU4400-01-00", "CLOSE": "", "SCOPE": "", "SEC": "", "JONGNM": "전필", "HYHG": "20202", "FIELD": "", "PRTYPE2": "3", "OHAKKWA": "04201", "EKNA": "INDEPENDENT STUDY", "MILE2YN": "", "NO_SLI": "Y" }, { "SUBJECT": "", "CLOSE5": "N", "CLOSE4": "N", "SBB": "00", "HAKBB": "MEU4400-02", "CLOSE1": "N", "PSOSOKNA": "공과대학 기계공학과", "OUTER_YN": "X", "CLOSE3": "N", "CLOSE2": "N", "JONG": "4", "GUBUN": "ⓖ⒝", "INTER": "", "HY": "2020", "BB": "02", "ONAME2": "기계공학전공", "NEWHAKNO": "D00917", "WEIGHT": "4000", "LINK": "", "KNA": "연구논문", "HAKNO": "MEU4400", "MILEYN": "", "DOMAIN": "H1", "HAKYOUN": "4", "HAKJUM": "3", "ROOM": "동영상콘텐츠/실시간온라인", "PROF": "민병권,주철민,조형희", "HG": "2", "TIME": "월6/수5,6", "BAN": "0", "OCODE1": "s1104000H1", "HAKBBSBB": "MEU4400-02-00", "CLOSE": "", "SCOPE": "", "SEC": "", "JONGNM": "전필", "HYHG": "20202", "FIELD": "", "PRTYPE2": "3", "OHAKKWA": "04201", "EKNA": "INDEPENDENT STUDY", "MILE2YN": "", "NO_SLI": "Y" }, { "SUBJECT": "", "CLOSE5": "N", "CLOSE4": "N", "SBB": "00", "HAKBB": "MEU4400-03", "CLOSE1": "N", "PSOSOKNA": "공과대학 기계공학과", "OUTER_YN": "X", "CLOSE3": "N", "CLOSE2": "N", "JONG": "4", "GUBUN": "ⓖ⒝", "INTER": "", "HY": "2020", "BB": "03", "ONAME2": "기계공학전공", "NEWHAKNO": "D00917", "WEIGHT": "4000", "LINK": "", "KNA": "연구논문", "HAKNO": "MEU4400", "MILEYN": "", "DOMAIN": "H1", "HAKYOUN": "4", "HAKJUM": "3", "ROOM": "동영상콘텐츠/실시간온라인", "PROF": "주철민,조형희,민병권", "HG": "2", "TIME": "월6/수5,6", "BAN": "0", "OCODE1": "s1104000H1", "HAKBBSBB": "MEU4400-03-00", "CLOSE": "", "SCOPE": "", "SEC": "", "JONGNM": "전필", "HYHG": "20202", "FIELD": "", "PRTYPE2": "3", "OHAKKWA": "04201", "EKNA": "INDEPENDENT STUDY", "MILE2YN": "", "NO_SLI": "Y" }] }
